pyotc/VERSION.txt
pyotc/__init__.py
pyotc/data_parser.py
pyotc/focal_shift.py
pyotc/height_calibration.py
pyotc/name_constants.py
pyotc/physics.py
pyotc/plotting.py
pyotc/psd.py
pyotc/psd_fitting.py
pyotc/utilities.py
pyoti/VERSION.txt
pyoti/__init__.py
pyoti/config.py
pyoti/experiment.py
pyoti/graph.py
pyoti/gui.py
pyoti/helpers.py
pyoti/picklable.py
pyoti/traces.py
pyoti/update.py
pyoti/calibration/__init__.py
pyoti/calibration/calibration.py
pyoti/calibration/calibsource.py
pyoti/configs/calibration.cfg
pyoti/configs/groups.cfg
pyoti/configs/record.cfg
pyoti/configs/traces.cfg
pyoti/configs/record/GenericData.cfg
pyoti/configs/record/GenericDataFile.cfg
pyoti/data/__init__.py
pyoti/data/datasource.py
pyoti/evaluate/__init__.py
pyoti/evaluate/evaluate.py
pyoti/evaluate/motion.py
pyoti/evaluate/signal.py
pyoti/evaluate/signalfeature.py
pyoti/evaluate/tether.py
pyoti/modification/__init__.py
pyoti/modification/modification.py
pyoti/plugins/__init__.py
pyoti/plugins/h5py.py
pyoti/plugins/plugin_loader.py
pyoti/plugins/calibsources/cellnano.py
pyoti/plugins/calibsources/pyotic.py
pyoti/plugins/datasources/cellnano.py
pyoti/plugins/datasources/generic.py
pyoti/plugins/modifications/attachment.py
pyoti/plugins/modifications/baseline.py
pyoti/plugins/modifications/beadscan.py
pyoti/plugins/modifications/generic.py
pyoti/plugins/modifications/offset.py
pyoti/plugins/modifications/rotation.py
pyoti/plugins/modifications/touchdown.py
pyoti/region/__init__.py
pyoti/region/record.py
pyoti/region/region.py
pyoti/region/view.py
pyotic-0.17.4.dist-info/LICENSE.txt
pyotic-0.17.4.dist-info/METADATA
pyotic-0.17.4.dist-info/WHEEL
pyotic-0.17.4.dist-info/top_level.txt
pyotic-0.17.4.dist-info/RECORD
