Metadata-Version: 2.1
Name: pyotic
Version: 0.17.4
Summary: Time-dependent signal analysis and calibration of optical tweezers.
Home-page: https://github.com/cellular-nanoscience/pyotic
Author: Tobias Jachowski and Steve Simmert
Author-email: steve.simmert@uni-tuebingen.de
License: Apache-2.0
Platform: Windows
Platform: Linux
Platform: Mac OS X
Classifier: Intended Audience :: Science/Research
Classifier: Intended Audience :: Education
Classifier: Framework :: Jupyter
Classifier: License :: OSI Approved :: Apache Software License
Classifier: Operating System :: OS Independent
Classifier: Programming Language :: Python
Classifier: Topic :: Scientific/Engineering :: Physics
Classifier: Topic :: Scientific/Engineering :: Visualization
Requires-Python: >=3, <4
